Workbook

Sheet Stores
A1: Store sales and value per sale
A2: Blue = typed from the data pack (currency assumed GBP, millions; "number of sales" assumed transactions, millions). Black = formula.
A4: Store | B4: Sales FY-4 | C4: Sales FY-3 | D4: Sales FY-2 | E4: Sales FY-1 | F4: Sales change FY-2 to FY-1 | G4: No. of sales FY-2 | H4: No. of sales FY-1 | I4: No. of sales change | J4: Value per sale FY-2 (GBP) | K4: Value per sale FY-1 (GBP) | L4: Value per sale change
A5: London | B5: 367.2 | C5: 389.2 | D5: 602.7 | E5: 563.8 | F5: =E5/D5-1 -> -0.06454289 | G5: 8.4 | H5: 9 | I5: =H5/G5-1 -> 0.071428571 | J5: =D5*1000/(G5*1000) -> 71.75 | K5: =E5/H5 -> 62.644444 | L5: =K5/J5-1 -> -0.1269067
A6: Birmingham | B6: 305.1 | C6: 320.5 | D6: 433.8 | E6: 470.3 | F6: =E6/D6-1 -> 0.084140157 | G6: 3.8 | H6: 4.1 | I6: =H6/G6-1 -> 0.078947368 | J6: =D6*1000/(G6*1000) -> 114.15789 | K6: =E6/H6 -> 114.70732 | L6: =K6/J6-1 -> 0.0048128282
A7: Edinburgh | B7: 92.4 | C7: 120.3 | D7: 134.2 | E7: 131.8 | F7: =E7/D7-1 -> -0.017883756 | G7: 2 | H7: 2.2 | I7: =H7/G7-1 -> 0.1 | J7: =D7*1000/(G7*1000) -> 67.1 | K7: =E7/H7 -> 59.909091 | L7: =K7/J7-1 -> -0.10716705
A8: Orlando | D8: 100 | E8: 91 | F8: =E8/D8-1 -> -0.09 | G8: 2.8 | H8: 3 | I8: =H8/G8-1 -> 0.071428571 | J8: =D8*1000/(G8*1000) -> 35.714286 | K8: =E8/H8 -> 30.333333 | L8: =K8/J8-1 -> -0.15066667
A9: All stores | D9: =SUM(D5:D8) -> 1270.7 | E9: =SUM(E5:E8) -> 1256.9 | F9: =E9/D9-1 -> -0.010860156 | G9: =SUM(G5:G8) -> 17 | H9: =SUM(H5:H8) -> 18.3 | I9: =H9/G9-1 -> 0.076470588 | J9: =D9/G9 -> 74.747059 | K9: =E9/H9 -> 68.68306 | L9: =K9/J9-1 -> -0.081126921
A11: Reading: sales count is up in every store, but value per sale fell in London, Edinburgh and Orlando; only Birmingham rose.
A12: Caveat: the "UK Profit" figures in the sales sheet do not reconcile to the P&L, so they are not used here.

Sheet PnL FY-1
A1: FY-1 P&L by channel (GBP)
A2: Blue = typed from the P&L image. Ratios are formulas. Check column should be zero.
A4: Channel | B4: Revenue | C4: Cost of sales | D4: Gross profit | E4: Logistics | F4: Admin | G4: EBIT (as reported) | H4: Gross margin | I4: Logistics % revenue | J4: Admin % revenue | K4: EBIT margin | L4: Check: GP-Log-Admin-EBIT
A5: London | B5: 563817683 | C5: 369931247 | D5: 193886436 | E5: 100820947 | F5: 49052138 | G5: 44013351 | H5: =D5/B5 -> 0.34388144 | I5: =E5/B5 -> 0.17881835 | J5: =F5/B5 -> 0.086999999 | K5: =G5/B5 -> 0.078063091 | L5: =D5-E5-F5-G5 -> 0
A6: Birmingham | B6: 470263012 | C6: 309638374 | D6: 160624638 | E6: 80312319 | F6: 41853408 | G6: 38458911 | H6: =D6/B6 -> 0.34156341 | I6: =E6/B6 -> 0.17078171 | J6: =F6/B6 -> 0.089 | K6: =G6/B6 -> 0.081781705 | L6: =D6-E6-F6-G6 -> 0
A7: Edinburgh | B7: 131771465 | C7: 88023884 | D7: 43747581 | E7: 27123500 | F7: 12122975 | G7: 4501106 | H7: =D7/B7 -> 0.33199586 | I7: =E7/B7 -> 0.20583743 | J7: =F7/B7 -> 0.092000002 | K7: =G7/B7 -> 0.034158427 | L7: =D7-E7-F7-G7 -> 0
A8: Orlando | B8: 90988681 | C8: 60074715 | D8: 30913965 | E8: 12056446 | F8: 4731411 | G8: 14126107 | H8: =D8/B8 -> 0.33975616 | I8: =E8/B8 -> 0.1325049 | J8: =F8/B8 -> 0.051999995 | K8: =G8/B8 -> 0.15525126 | L8: =D8-E8-F8-G8 -> 1
A9: Online | B9: 5654213 | C9: 3844865 | D9: 1809348 | E9: 948211 | F9: 510575 | G9: 350561 | H9: =D9/B9 -> 0.31999997 | I9: =E9/B9 -> 0.16769991 | J9: =F9/B9 -> 0.090299923 | K9: =G9/B9 -> 0.061999964 | L9: =D9-E9-F9-G9 -> 1
A10: Group | B10: =SUM(B5:B9) -> 1262495054 | C10: =SUM(C5:C9) -> 831513085 | D10: =SUM(D5:D9) -> 430981968 | E10: =SUM(E5:E9) -> 221261423 | F10: =SUM(F5:F9) -> 108270507 | G10: =SUM(G5:G9) -> 101450036 | H10: =D10/B10 -> 0.34137319 | I10: =E10/B10 -> 0.17525726 | J10: =F10/B10 -> 0.085759153 | K10: =G10/B10 -> 0.080356779 | L10: =D10-E10-F10-G10 -> 2
A12: Reported group revenue | B12: 1262495054
A13: Difference to sum of channels | B13: =B10-B12 -> 0
A14: Reported group EBIT | B14: 101450036
A15: Difference to sum of channels | B15: =G10-B14 -> 0
A17: Reading: Edinburgh logistics are ~20.6% of revenue vs ~17.5% for the group; Orlando EBIT margin may reflect cost allocation.

Sheet Ambition
A1: Ambition arithmetic (not a forecast)
A2: Blue = inputs. The 10% EBIT target and GBP 2bn revenue come from the client brief.
A4: Group revenue FY-1 (GBP m) | B4: ='PnL FY-1'!B10/1000000 -> 1262.4951
A5: Group EBIT FY-1 (GBP m) | B5: ='PnL FY-1'!G10/1000000 -> 101.45004
A6: Current EBIT margin | B6: =B5/B4 -> 0.080356779
A7: Target EBIT margin | B7: 0.1
A8: EBIT at target margin on current revenue (GBP m) | B8: =B4*B7 -> 126.24951
A9: EBIT gap (GBP m) | B9: =B8-B5 -> 24.799469
A10: Value of 1 point of margin (GBP m) | B10: =B4*0.01 -> 12.624951
A11: Revenue ambition (GBP m) | B11: 2000
A12: Years to ambition | B12: 5 | C12: Assumption: five-year horizon is ours, not the client's.
A13: Growth required | B13: =B11/B4-1 -> 0.58416462
A14: Implied annual growth (CAGR) | B14: =(B11/B4)^(1/B12)-1 -> 0.096377368
A15: Edinburgh logistics % revenue | B15: ='PnL FY-1'!I7 -> 0.20583743
A16: Group logistics % revenue | B16: ='PnL FY-1'!I10 -> 0.17525726
A17: Saving if Edinburgh hit group logistics ratio (GBP m) | B17: =('PnL FY-1'!E7-'PnL FY-1'!B7*B16)/1000000 -> 4.0295942

Sheet Online
A1: Website visits (data pack)
A2: Blue = typed from the website data images. Page figures are views, keyword figures are visits: do not mix.
A4: Traffic source | B4: Visits | C4: Share
A5: Source 1 (largest) | B5: 455796 | C5: =B5/$B$9 -> 0.46408219
A6: Source 2 | B6: 214688 | C6: =B6/$B$9 -> 0.21859094
A7: Source 3 | B7: 169087 | C7: =B7/$B$9 -> 0.17216093
A8: Source 4 | B8: 142574 | C8: =B8/$B$9 -> 0.14516594
A9: Total | B9: =SUM(B5:B8) -> 982145 | C9: =B9/B9 -> 1
A10: Note: source names should be checked against the original image before quoting.
A12: Country | B12: Visits | C12: Share
A13: UK | B13: 412501 | C13: =B13/$B$24 -> 0.4200001
A14: Country 2 | B14: 284822 | C14: =B14/$B$24 -> 0.28999995
A15: Country 3 | B15: 127679 | C15: =B15/$B$24 -> 0.13000015
A16: Country 4 | B16: 58929 | C16: =B16/$B$24 -> 0.060000305
A17: Country 5 | B17: 39286 | C17: =B17/$B$24 -> 0.040000204
A18: Country 6 | B18: 35357 | C18: =B18/$B$24 -> 0.035999776
A19: Country 7 | B19: 19643 | C19: =B19/$B$24 -> 0.020000102
A20: Country 8 | B20: 2946 | C20: =B20/$B$24 -> 0.0029995571
A21: Country 9 | B21: 491 | C21: =B21/$B$24 -> 0.00049992618
A22: Country 10 | B22: 295 | C22: =B22/$B$24 -> 0.00030036298
A23: Country 11 | B23: 196 | C23: =B23/$B$24 -> 0.0001995632
A24: Total | B24: =SUM(B13:B23) -> 982145 | C24: =B24/B24 -> 1
A25: Non-UK share | C25: =1-B13/B24 -> 0.5799999
A27: Online revenue FY-1 (GBP) | B27: ='PnL FY-1'!B9 -> 5654213
A28: Revenue per visit (GBP) | B28: =B27/B24 -> 5.7570043
A29: Help pages views (contact us + delivery FAQ) | B29: =142411+137500 -> 279911
A30: Womenswear page views | B30: 147322
A31: Help vs womenswear | B31: =B29/B30 -> 1.8999946
A32: Golf keyword visits | B32: 105384
A33: Golf share of visits | B33: =B32/B24 -> 0.10729984

Sheet Assumptions and caveats
A1: What we assumed and what to verify
A2: Say these out loud before anyone quotes a number.
A4: # | B4: Assumption or caveat | C4: How to resolve | D4: Owner (suggested)
A5: 1 | B5: Currency is GBP for all figures, including Orlando | C5: Confirm with Ashley | D5: Ashley
A6: 2 | B6: "Number of sales" means transactions | C6: Confirm definition with Jesse | D6: Jesse
A7: 3 | B7: "UK Profit" in the sales sheet does not reconcile to the P&L; Orlando "profit" looks like gross profit | C7: Ask Ashley which definition the sales sheet uses | D7: Ashley
A8: 4 | B8: Page figures are views; keyword figures are visits | C8: Keep separate in every slide | D8: Team
A9: 5 | B9: Referral-site visits are blank in the data | C9: Request the referral split | D9: Anshu
A10: 6 | B10: Orlando 15.5% EBIT margin may reflect cost allocation | C10: Ask how shared costs are allocated | D10: Ashley
A11: 7 | B11: No online conversion data supplied | C11: Request funnel and conversion by country | D11: Anshu
A12: 8 | B12: 10% EBIT gap and 9.6% CAGR are arithmetic, not forecasts | C12: Frame as scale of ambition | D12: Team
A13: 9 | B13: Pitch slot and date: email says "later this week" | C13: Confirm slot length and date | D13: Team

Sheet Data requests
A1: Data requests before the pitch
A2: Example row shows the expected format. Edit status in column F.
A4: # | B4: Request | C4: Why it matters | D4: Ask | E4: Needed by | F4: Status
A5: 1 | B5: Online conversion and funnel by country | C5: Tests whether friction, not demand, caps online | D5: Anshu | E5: Before pitch | F5: Open
A6: 2 | B6: Store-level P&L with allocation rules | C6: Tests Orlando and Edinburgh margins | D6: Ashley | E6: Before pitch | F6: Open
A7: 3 | B7: Definition of "profit" in the sales sheet | C7: Reconcile to the P&L | D7: Ashley | E7: Day 1 | F7: Open
A8: 4 | B8: Basket mix by store (categories, brands) | C8: Explains falling value per sale | D8: Jesse | E8: Day 2 | F8: Open
A9: 5 | B9: Delivery and returns volumes and cost by route | C9: Sizes the logistics opportunity | D9: Ashley | E9: Day 2 | F9: Open
A10: 6 | B10: Stock-order cycle times by step | C10: Quantifies the four pain points | D10: Jesse | E10: Day 2 | F10: Open
A11: 7 | B11: Referral-site traffic and golf-related sales | C11: Sizes the golf niche | D11: Anshu | E11: Day 2 | F11: Open
